funserver/__init__.py
funserver/servers/__init__.py
funserver/servers/onehub.py
funserver/servers/base/__init__.py
funserver/servers/base/base.py
funserver/servers/base/install.py
funserver/servers/base/start.py
funserver/servers/funjupyter/__init__.py
funserver/servers/funjupyter/config.py
funserver/servers/funjupyter/run.py
funserver-1.0.54.dist-info/METADATA
funserver-1.0.54.dist-info/WHEEL
funserver-1.0.54.dist-info/entry_points.txt
funserver-1.0.54.dist-info/top_level.txt
funserver-1.0.54.dist-info/RECORD
