Metadata-Version: 2.4
Name: funserver
Version: 1.0.54
Summary: funserver
Author-email: 牛哥 <niuliangtao@qq.com>, farfarfun <farfarfun@qq.com>
Maintainer-email: 牛哥 <niuliangtao@qq.com>, farfarfun <farfarfun@qq.com>
Project-URL: Organization, https://github.com/farfarfun
Project-URL: Repository, https://github.com/farfarfun/funserver
Project-URL: Releases, https://github.com/farfarfun/funserver/releases
Requires-Python: >=3.8
Requires-Dist: click>=8.1.8
Requires-Dist: funbuild>=1.5.11
Requires-Dist: funutil>=1.0.50
Requires-Dist: psutil>=7.0.0
Requires-Dist: typer>=0.15.3
